django_webpack_loader-3.2.2.dist-info/licenses/LICENSE
django_webpack_loader-3.2.2.dist-info/licenses/LICENSE.txt
webpack_loader/__init__.py
webpack_loader/apps.py
webpack_loader/config.py
webpack_loader/errors.py
webpack_loader/exceptions.py
webpack_loader/loader.py
webpack_loader/loaders.py
webpack_loader/signals.py
webpack_loader/utils.py
webpack_loader/contrib/__init__.py
webpack_loader/contrib/jinja2ext.py
webpack_loader/templatetags/__init__.py
webpack_loader/templatetags/webpack_loader.py
django_webpack_loader-3.2.2.dist-info/METADATA
django_webpack_loader-3.2.2.dist-info/WHEEL
django_webpack_loader-3.2.2.dist-info/top_level.txt
django_webpack_loader-3.2.2.dist-info/RECORD
