Metadata-Version: 2.4
Name: django-webpack-loader
Version: 3.2.2
Summary: Transparently use webpack with django
Home-page: https://github.com/django-webpack/django-webpack-loader
Download-URL: https://github.com/django-webpack/django-webpack-loader/tarball/3.2.2
Author: Vinta Software
Author-email: contact@vinta.com.br
License: MIT License
Keywords: django,webpack,assets
Classifier: Programming Language :: Python
Classifier: Programming Language :: Python :: 3.8
Classifier: Programming Language :: Python :: 3.9
Classifier: Programming Language :: Python :: 3.10
Classifier: Programming Language :: Python :: 3.11
Classifier: Programming Language :: Python :: 3.12
Classifier: Programming Language :: Python :: 3.13
Classifier: Framework :: Django
Classifier: Framework :: Django :: 4.2
Classifier: Framework :: Django :: 5.0
Classifier: Framework :: Django :: 5.1
Classifier: Framework :: Django :: 5.2
Classifier: Environment :: Web Environment
Classifier: License :: OSI Approved :: MIT License
License-File: LICENSE
License-File: LICENSE.txt
Dynamic: author
Dynamic: author-email
Dynamic: classifier
Dynamic: description
Dynamic: description-content-type
Dynamic: download-url
Dynamic: home-page
Dynamic: keywords
Dynamic: license
Dynamic: license-file
Dynamic: summary
